[1,["17c6be44a@6c48a"],["_textureSource"],["cc.SpriteFrame"],0,[[[{"name":"frame_53_delay-0.1s","rect":{"x":3,"y":334,"width":666,"height":324},"offset":{"x":0,"y":-25.5},"originalSize":{"width":666,"height":375},"rotated":false,"capInsets":[0,0,0,0],"packable":true,"pixelsToUnit":100,"pivot":{"x":0.5,"y":0.5},"meshType":0}],[0],0,[0],[0],[0]],[[{"name":"frame_50_delay-0.1s","rect":{"x":3,"y":3,"width":666,"height":325},"offset":{"x":0,"y":-25},"originalSize":{"width":666,"height":375},"rotated":false,"capInsets":[0,0,0,0],"packable":true,"pixelsToUnit":100,"pivot":{"x":0.5,"y":0.5},"meshType":0}],[0],0,[0],[0],[0]],[[{"name":"frame_59_delay-0.1s","rect":{"x":675,"y":3,"width":589,"height":325},"offset":{"x":-7.5,"y":-25},"originalSize":{"width":666,"height":375},"rotated":true,"capInsets":[0,0,0,0],"packable":true,"pixelsToUnit":100,"pivot":{"x":0.5,"y":0.5},"meshType":0}],[0],0,[0],[0],[0]],[[{"name":"frame_71_delay-0.1s","rect":{"x":675,"y":598,"width":409,"height":272},"offset":{"x":5.5,"y":0.5},"originalSize":{"width":666,"height":375},"rotated":true,"capInsets":[0,0,0,0],"packable":true,"pixelsToUnit":100,"pivot":{"x":0.5,"y":0.5},"meshType":0}],[0],0,[0],[0],[0]],[[{"name":"frame_51_delay-0.1s","rect":{"x":3,"y":664,"width":666,"height":323},"offset":{"x":0,"y":-26},"originalSize":{"width":666,"height":375},"rotated":false,"capInsets":[0,0,0,0],"packable":true,"pixelsToUnit":100,"pivot":{"x":0.5,"y":0.5},"meshType":0}],[0],0,[0],[0],[0]]]]
